{"results":[{"address_components":[{"long_name":"Haizer","short_name":"Haizer","types":["locality","political"]},{"long_name":"Wilaya de Bouira","short_name":"Wilaya de Bouira","types":["administrative_area_level_1","political"]},{"long_name":"Algérie","short_name":"DZ","types":["country","political"]}],"formatted_address":"Haizer, Algérie","geometry":{"bounds":{"northeast":{"lat":36.4681639,"lng":4.1002179},"southwest":{"lat":36.3456186,"lng":3.9373113}},"location":{"lat":36.4328965,"lng":4.0491077},"location_type":"APPROXIMATE","viewport":{"northeast":{"lat":36.4681639,"lng":4.1002179},"southwest":{"lat":36.3456186,"lng":3.9373113}}},"place_id":"ChIJZwwJJ98wjBIRD4R9dvR-Imo","types":["locality","political"]}],"status":"OK"}