{"results":[{"address_components":[{"long_name":"Sidi Ladjel","short_name":"Sidi Ladjel","types":["locality","political"]},{"long_name":"Wilaya de Djelfa","short_name":"Wilaya de Djelfa","types":["administrative_area_level_1","political"]},{"long_name":"Algérie","short_name":"DZ","types":["country","political"]}],"formatted_address":"Sidi Ladjel, Algérie","geometry":{"bounds":{"northeast":{"lat":35.4581531,"lng":2.5296021},"southwest":{"lat":35.4285747,"lng":2.493639}},"location":{"lat":35.435674,"lng":2.514842},"location_type":"APPROXIMATE","viewport":{"northeast":{"lat":35.4581531,"lng":2.5296021},"southwest":{"lat":35.4285747,"lng":2.493639}}},"place_id":"ChIJM6-RFzmciBIRNvpMLypAtYo","types":["locality","political"]}],"status":"OK"}