{"results":[{"address_components":[{"long_name":"Ain Arnat","short_name":"Ain Arnat","types":["locality","political"]},{"long_name":"Wilaya de Sétif","short_name":"Wilaya de Sétif","types":["administrative_area_level_1","political"]},{"long_name":"Algérie","short_name":"DZ","types":["country","political"]}],"formatted_address":"Ain Arnat, Algérie","geometry":{"bounds":{"northeast":{"lat":36.2523026,"lng":5.3510284},"southwest":{"lat":36.0990478,"lng":5.1350785}},"location":{"lat":36.1900716,"lng":5.3163224},"location_type":"APPROXIMATE","viewport":{"northeast":{"lat":36.2523026,"lng":5.3510284},"southwest":{"lat":36.0990478,"lng":5.1350785}}},"partial_match":true,"place_id":"ChIJRZQxpyw_8xIRdCiXyBVrJYU","types":["locality","political"]}],"status":"OK"}