{"results":[{"address_components":[{"long_name":"Maoklane","short_name":"Maoklane","types":["locality","political"]},{"long_name":"Wilaya de Sétif","short_name":"Wilaya de Sétif","types":["administrative_area_level_1","political"]},{"long_name":"Algérie","short_name":"DZ","types":["country","political"]}],"formatted_address":"Maoklane, Algérie","geometry":{"bounds":{"northeast":{"lat":36.4466793,"lng":5.1798258},"southwest":{"lat":36.3557652,"lng":5.0136255}},"location":{"lat":36.3966491,"lng":5.0769287},"location_type":"APPROXIMATE","viewport":{"northeast":{"lat":36.4466793,"lng":5.1798258},"southwest":{"lat":36.3557652,"lng":5.0136255}}},"partial_match":true,"place_id":"ChIJ34cqsrks8xIRL3e4t3CsZCA","types":["locality","political"]}],"status":"OK"}