{"results":[{"address_components":[{"long_name":"Belarbi","short_name":"Belarbi","types":["locality","political"]},{"long_name":"Wilaya de Sidi Bel Abbès","short_name":"Wilaya de Sidi Bel Abbès","types":["administrative_area_level_1","political"]},{"long_name":"Algérie","short_name":"DZ","types":["country","political"]}],"formatted_address":"Belarbi, Algérie","geometry":{"bounds":{"northeast":{"lat":35.1907849,"lng":-0.3747368},"southwest":{"lat":35.0712419,"lng":-0.519104}},"location":{"lat":35.1370812,"lng":-0.4408037},"location_type":"APPROXIMATE","viewport":{"northeast":{"lat":35.1907849,"lng":-0.3747368},"southwest":{"lat":35.0712419,"lng":-0.519104}}},"place_id":"ChIJWX5vuo2tfw0RR1g7WpH1sc8","types":["locality","political"]}],"status":"OK"}