{"results":[{"address_components":[{"long_name":"Oued Cheham","short_name":"Oued Cheham","types":["locality","political"]},{"long_name":"Wilaya de Guelma","short_name":"Wilaya de Guelma","types":["administrative_area_level_1","political"]},{"long_name":"Algérie","short_name":"DZ","types":["country","political"]}],"formatted_address":"Oued Cheham, Algérie","geometry":{"bounds":{"northeast":{"lat":36.3900931,"lng":7.7774619},"southwest":{"lat":36.3727487,"lng":7.758407599999999}},"location":{"lat":36.38248189999999,"lng":7.767477299999999},"location_type":"APPROXIMATE","viewport":{"northeast":{"lat":36.3900931,"lng":7.7774619},"southwest":{"lat":36.3727487,"lng":7.758407599999999}}},"place_id":"ChIJMauNZZR_8BIRILlDqaUFvj4","types":["locality","political"]}],"status":"OK"}