{"results":[{"address_components":[{"long_name":"Benzouh","short_name":"Benzouh","types":["locality","political"]},{"long_name":"Wilaya de M'Sila","short_name":"Wilaya de M'Sila","types":["administrative_area_level_1","political"]},{"long_name":"Algérie","short_name":"DZ","types":["country","political"]}],"formatted_address":"Benzouh, Algérie","geometry":{"bounds":{"northeast":{"lat":35.6026022,"lng":4.266300300000001},"southwest":{"lat":35.3097672,"lng":3.9880371}},"location":{"lat":35.474817,"lng":4.0899911},"location_type":"APPROXIMATE","viewport":{"northeast":{"lat":35.6026022,"lng":4.266300300000001},"southwest":{"lat":35.3097672,"lng":3.9880371}}},"place_id":"ChIJJ_8mDkDDixIRMoDG5POFh9w","types":["locality","political"]}],"status":"OK"}