{"results":[{"address_components":[{"long_name":"Aïn Fares","short_name":"Aïn Fares","types":["locality","political"]},{"long_name":"Wilaya de Mascara","short_name":"Wilaya de Mascara","types":["administrative_area_level_1","political"]},{"long_name":"Algérie","short_name":"DZ","types":["country","political"]}],"formatted_address":"Aïn Fares, Algérie","geometry":{"bounds":{"northeast":{"lat":35.5408521,"lng":0.2891635},"southwest":{"lat":35.4152855,"lng":0.1903725}},"location":{"lat":35.4560355,"lng":0.2432307},"location_type":"APPROXIMATE","viewport":{"northeast":{"lat":35.5408521,"lng":0.2891635},"southwest":{"lat":35.4152855,"lng":0.1903725}}},"place_id":"ChIJmyVbQkvBgRIRaXJ7fwgTgPk","types":["locality","political"]}],"status":"OK"}