{"results":[{"address_components":[{"long_name":"Mascara","short_name":"Mascara","types":["locality","political"]},{"long_name":"Wilaya de Mascara","short_name":"Wilaya de Mascara","types":["administrative_area_level_1","political"]},{"long_name":"Algérie","short_name":"DZ","types":["country","political"]}],"formatted_address":"Mascara, Algérie","geometry":{"bounds":{"northeast":{"lat":35.434834,"lng":0.2146196},"southwest":{"lat":35.331162,"lng":0.0938987}},"location":{"lat":35.3974554,"lng":0.1388446},"location_type":"APPROXIMATE","viewport":{"northeast":{"lat":35.434834,"lng":0.2146196},"southwest":{"lat":35.331162,"lng":0.0938987}}},"partial_match":true,"place_id":"ChIJGc14XqXagRIRrPDWOkDkqnA","types":["locality","political"]}],"status":"OK"}