{"results":[{"address_components":[{"long_name":"Bordj Omar Driss","short_name":"Bordj Omar Driss","types":["locality","political"]},{"long_name":"Wilaya d'Illizi","short_name":"Wilaya d'Illizi","types":["administrative_area_level_1","political"]},{"long_name":"Algérie","short_name":"DZ","types":["country","political"]}],"formatted_address":"Bordj Omar Driss, Algérie","geometry":{"bounds":{"northeast":{"lat":28.1242993,"lng":6.7914392},"southwest":{"lat":28.099998,"lng":6.7263793}},"location":{"lat":28.115695,"lng":6.7547522},"location_type":"APPROXIMATE","viewport":{"northeast":{"lat":28.1242993,"lng":6.7914392},"southwest":{"lat":28.099998,"lng":6.7263793}}},"place_id":"ChIJbbfO3aLqOBIRUOxCgV4ZmLM","types":["locality","political"]}],"status":"OK"}