{"results":[{"address_components":[{"long_name":"Ourmas","short_name":"Ourmas","types":["locality","political"]},{"long_name":"Wilaya d'El Oued","short_name":"Wilaya d'El Oued","types":["administrative_area_level_1","political"]},{"long_name":"Algérie","short_name":"DZ","types":["country","political"]}],"formatted_address":"Ourmas, Algérie","geometry":{"bounds":{"northeast":{"lat":33.430725,"lng":6.7850018},"southwest":{"lat":33.3965328,"lng":6.7723418}},"location":{"lat":33.4141525,"lng":6.7828626},"location_type":"APPROXIMATE","viewport":{"northeast":{"lat":33.430725,"lng":6.7850018},"southwest":{"lat":33.3965328,"lng":6.7723418}}},"partial_match":true,"place_id":"ChIJ6WoOC-wXWRIR050_ZWJY-PY","types":["locality","political"]}],"status":"OK"}