{"results":[{"address_components":[{"long_name":"Assela","short_name":"Assela","types":["locality","political"]},{"long_name":"Wilaya de Naâma","short_name":"Wilaya de Naâma","types":["administrative_area_level_1","political"]},{"long_name":"Algérie","short_name":"DZ","types":["country","political"]}],"formatted_address":"Assela, Algérie","geometry":{"bounds":{"northeast":{"lat":33.0216902,"lng":-0.0626564},"southwest":{"lat":32.9872119,"lng":-0.094328}},"location":{"lat":33.005701,"lng":-0.0793488},"location_type":"APPROXIMATE","viewport":{"northeast":{"lat":33.0216902,"lng":-0.0626564},"southwest":{"lat":32.9872119,"lng":-0.094328}}},"place_id":"ChIJ2UBu441Thw0RZLe_SzvhV4U","types":["locality","political"]}],"status":"OK"}