{"results":[{"address_components":[{"long_name":"Béni Abbès","short_name":"Béni Abbès","types":["locality","political"]},{"long_name":"Wilaya de Béchar","short_name":"Wilaya de Béchar","types":["administrative_area_level_1","political"]},{"long_name":"Algérie","short_name":"DZ","types":["country","political"]}],"formatted_address":"Béni Abbès, Algérie","geometry":{"bounds":{"northeast":{"lat":30.1377139,"lng":-2.1553588},"southwest":{"lat":30.1227465,"lng":-2.1836401}},"location":{"lat":30.1324686,"lng":-2.1671288},"location_type":"APPROXIMATE","viewport":{"northeast":{"lat":30.1377139,"lng":-2.1553588},"southwest":{"lat":30.1227465,"lng":-2.1836401}}},"place_id":"ChIJNb2ufiPgjQ0RijsOLHUtqIA","types":["locality","political"]}],"status":"OK"}